pytest_failed_screen_record.py
pytest_failed_screen_record-0.1.2.dist-info/entry_points.txt
pytest_failed_screen_record-0.1.2.dist-info/LICENSE
pytest_failed_screen_record-0.1.2.dist-info/WHEEL
pytest_failed_screen_record-0.1.2.dist-info/METADATA
pytest_failed_screen_record-0.1.2.dist-info/RECORD
