Metadata-Version: 2.1
Name: pytest-failed-screen-record
Version: 0.1.2
Summary: Create a video of the screen when pytest fails
Home-page: https://github.com/KeisukeShima/pytest-failed-screen-record
License: MIT
Author: Keisuke Shima
Author-email: 19993104+KeisukeShima@users.noreply.github.com
Requires-Python: >=3.8,<4.0
Classifier: Development Status :: 4 - Beta
Classifier: Framework :: Pytest
Classifier: Intended Audience :: Developers
Classifier: License :: OSI Approved :: MIT License
Classifier: Operating System :: OS Independent
Classifier: Programming Language :: Python
Classifier: Programming Language :: Python :: 3
Classifier: Programming Language :: Python :: 3 :: Only
Classifier: Programming Language :: Python :: 3.10
Classifier: Programming Language :: Python :: 3.8
Classifier: Programming Language :: Python :: 3.9
Classifier: Programming Language :: Python :: Implementation :: CPython
Classifier: Programming Language :: Python :: Implementation :: PyPy
Classifier: Topic :: Software Development :: Testing
Requires-Dist: DateTime (>=4.9,<5.0)
Requires-Dist: PyAutoGUI (>=0.9.53,<0.10.0)
Requires-Dist: numpy (>=1.23.5,<2.0.0)
Requires-Dist: opencv-python (>=4.6.0,<5.0.0)
Requires-Dist: pytest (>=7.1.2d,<8.0.0)
Project-URL: Repository, https://github.com/KeisukeShima/pytest-failed-screen-record
